[ {
  "name" : "com.azure.resourcemanager.sqlvirtualmachine.fluent.models.AvailabilityGroupListenerInner",
  "allDeclaredConstructors" : true,
  "allDeclaredFields" : true,
  "allDeclaredMethods" : true
}, {
  "name" : "com.azure.resourcemanager.sqlvirtualmachine.fluent.models.AvailabilityGroupListenerProperties",
  "allDeclaredConstructors" : true,
  "allDeclaredFields" : true,
  "allDeclaredMethods" : true
}, {
  "name" : "com.azure.resourcemanager.sqlvirtualmachine.models.LoadBalancerConfiguration",
  "allDeclaredConstructors" : true,
  "allDeclaredFields" : true,
  "allDeclaredMethods" : true
}, {
  "name" : "com.azure.resourcemanager.sqlvirtualmachine.models.PrivateIpAddress",
  "allDeclaredConstructors" : true,
  "allDeclaredFields" : true,
  "allDeclaredMethods" : true
}, {
  "name" : "com.azure.resourcemanager.sqlvirtualmachine.models.MultiSubnetIpConfiguration",
  "allDeclaredConstructors" : true,
  "allDeclaredFields" : true,
  "allDeclaredMethods" : true
}, {
  "name" : "com.azure.resourcemanager.sqlvirtualmachine.models.AgConfiguration",
  "allDeclaredConstructors" : true,
  "allDeclaredFields" : true,
  "allDeclaredMethods" : true
}, {
  "name" : "com.azure.resourcemanager.sqlvirtualmachine.models.AgReplica",
  "allDeclaredConstructors" : true,
  "allDeclaredFields" : true,
  "allDeclaredMethods" : true
}, {
  "name" : "com.azure.resourcemanager.sqlvirtualmachine.models.AvailabilityGroupListenerListResult",
  "allDeclaredConstructors" : true,
  "allDeclaredFields" : true,
  "allDeclaredMethods" : true
}, {
  "name" : "com.azure.resourcemanager.sqlvirtualmachine.models.OperationListResult",
  "allDeclaredConstructors" : true,
  "allDeclaredFields" : true,
  "allDeclaredMethods" : true
}, {
  "name" : "com.azure.resourcemanager.sqlvirtualmachine.fluent.models.OperationInner",
  "allDeclaredConstructors" : true,
  "allDeclaredFields" : true,
  "allDeclaredMethods" : true
}, {
  "name" : "com.azure.resourcemanager.sqlvirtualmachine.models.OperationDisplay",
  "allDeclaredConstructors" : true,
  "allDeclaredFields" : true,
  "allDeclaredMethods" : true
}, {
  "name" : "com.azure.resourcemanager.sqlvirtualmachine.fluent.models.SqlVirtualMachineGroupInner",
  "allDeclaredConstructors" : true,
  "allDeclaredFields" : true,
  "allDeclaredMethods" : true
}, {
  "name" : "com.azure.resourcemanager.sqlvirtualmachine.fluent.models.SqlVirtualMachineGroupProperties",
  "allDeclaredConstructors" : true,
  "allDeclaredFields" : true,
  "allDeclaredMethods" : true
}, {
  "name" : "com.azure.resourcemanager.sqlvirtualmachine.models.WsfcDomainProfile",
  "allDeclaredConstructors" : true,
  "allDeclaredFields" : true,
  "allDeclaredMethods" : true
}, {
  "name" : "com.azure.resourcemanager.sqlvirtualmachine.models.SqlVirtualMachineGroupUpdate",
  "allDeclaredConstructors" : true,
  "allDeclaredFields" : true,
  "allDeclaredMethods" : true
}, {
  "name" : "com.azure.resourcemanager.sqlvirtualmachine.models.SqlVirtualMachineGroupListResult",
  "allDeclaredConstructors" : true,
  "allDeclaredFields" : true,
  "allDeclaredMethods" : true
}, {
  "name" : "com.azure.resourcemanager.sqlvirtualmachine.models.SqlVirtualMachineListResult",
  "allDeclaredConstructors" : true,
  "allDeclaredFields" : true,
  "allDeclaredMethods" : true
}, {
  "name" : "com.azure.resourcemanager.sqlvirtualmachine.fluent.models.SqlVirtualMachineInner",
  "allDeclaredConstructors" : true,
  "allDeclaredFields" : true,
  "allDeclaredMethods" : true
}, {
  "name" : "com.azure.resourcemanager.sqlvirtualmachine.models.ResourceIdentity",
  "allDeclaredConstructors" : true,
  "allDeclaredFields" : true,
  "allDeclaredMethods" : true
}, {
  "name" : "com.azure.resourcemanager.sqlvirtualmachine.fluent.models.SqlVirtualMachineProperties",
  "allDeclaredConstructors" : true,
  "allDeclaredFields" : true,
  "allDeclaredMethods" : true
}, {
  "name" : "com.azure.resourcemanager.sqlvirtualmachine.models.WsfcDomainCredentials",
  "allDeclaredConstructors" : true,
  "allDeclaredFields" : true,
  "allDeclaredMethods" : true
}, {
  "name" : "com.azure.resourcemanager.sqlvirtualmachine.models.AutoPatchingSettings",
  "allDeclaredConstructors" : true,
  "allDeclaredFields" : true,
  "allDeclaredMethods" : true
}, {
  "name" : "com.azure.resourcemanager.sqlvirtualmachine.models.AutoBackupSettings",
  "allDeclaredConstructors" : true,
  "allDeclaredFields" : true,
  "allDeclaredMethods" : true
}, {
  "name" : "com.azure.resourcemanager.sqlvirtualmachine.models.KeyVaultCredentialSettings",
  "allDeclaredConstructors" : true,
  "allDeclaredFields" : true,
  "allDeclaredMethods" : true
}, {
  "name" : "com.azure.resourcemanager.sqlvirtualmachine.models.ServerConfigurationsManagementSettings",
  "allDeclaredConstructors" : true,
  "allDeclaredFields" : true,
  "allDeclaredMethods" : true
}, {
  "name" : "com.azure.resourcemanager.sqlvirtualmachine.models.SqlConnectivityUpdateSettings",
  "allDeclaredConstructors" : true,
  "allDeclaredFields" : true,
  "allDeclaredMethods" : true
}, {
  "name" : "com.azure.resourcemanager.sqlvirtualmachine.models.SqlWorkloadTypeUpdateSettings",
  "allDeclaredConstructors" : true,
  "allDeclaredFields" : true,
  "allDeclaredMethods" : true
}, {
  "name" : "com.azure.resourcemanager.sqlvirtualmachine.models.SqlStorageUpdateSettings",
  "allDeclaredConstructors" : true,
  "allDeclaredFields" : true,
  "allDeclaredMethods" : true
}, {
  "name" : "com.azure.resourcemanager.sqlvirtualmachine.models.AdditionalFeaturesServerConfigurations",
  "allDeclaredConstructors" : true,
  "allDeclaredFields" : true,
  "allDeclaredMethods" : true
}, {
  "name" : "com.azure.resourcemanager.sqlvirtualmachine.models.SqlInstanceSettings",
  "allDeclaredConstructors" : true,
  "allDeclaredFields" : true,
  "allDeclaredMethods" : true
}, {
  "name" : "com.azure.resourcemanager.sqlvirtualmachine.models.AadAuthenticationSettings",
  "allDeclaredConstructors" : true,
  "allDeclaredFields" : true,
  "allDeclaredMethods" : true
}, {
  "name" : "com.azure.resourcemanager.sqlvirtualmachine.models.StorageConfigurationSettings",
  "allDeclaredConstructors" : true,
  "allDeclaredFields" : true,
  "allDeclaredMethods" : true
}, {
  "name" : "com.azure.resourcemanager.sqlvirtualmachine.models.SqlStorageSettings",
  "allDeclaredConstructors" : true,
  "allDeclaredFields" : true,
  "allDeclaredMethods" : true
}, {
  "name" : "com.azure.resourcemanager.sqlvirtualmachine.models.SqlTempDbSettings",
  "allDeclaredConstructors" : true,
  "allDeclaredFields" : true,
  "allDeclaredMethods" : true
}, {
  "name" : "com.azure.resourcemanager.sqlvirtualmachine.models.TroubleshootingStatus",
  "allDeclaredConstructors" : true,
  "allDeclaredFields" : true,
  "allDeclaredMethods" : true
}, {
  "name" : "com.azure.resourcemanager.sqlvirtualmachine.models.TroubleshootingAdditionalProperties",
  "allDeclaredConstructors" : true,
  "allDeclaredFields" : true,
  "allDeclaredMethods" : true
}, {
  "name" : "com.azure.resourcemanager.sqlvirtualmachine.models.UnhealthyReplicaInfo",
  "allDeclaredConstructors" : true,
  "allDeclaredFields" : true,
  "allDeclaredMethods" : true
}, {
  "name" : "com.azure.resourcemanager.sqlvirtualmachine.models.AssessmentSettings",
  "allDeclaredConstructors" : true,
  "allDeclaredFields" : true,
  "allDeclaredMethods" : true
}, {
  "name" : "com.azure.resourcemanager.sqlvirtualmachine.models.Schedule",
  "allDeclaredConstructors" : true,
  "allDeclaredFields" : true,
  "allDeclaredMethods" : true
}, {
  "name" : "com.azure.resourcemanager.sqlvirtualmachine.models.SqlVirtualMachineUpdate",
  "allDeclaredConstructors" : true,
  "allDeclaredFields" : true,
  "allDeclaredMethods" : true
}, {
  "name" : "com.azure.resourcemanager.sqlvirtualmachine.fluent.models.SqlVmTroubleshootingInner",
  "allDeclaredConstructors" : true,
  "allDeclaredFields" : true,
  "allDeclaredMethods" : true
}, {
  "name" : "com.azure.resourcemanager.sqlvirtualmachine.models.Role",
  "allDeclaredConstructors" : true,
  "allDeclaredFields" : true,
  "allDeclaredMethods" : true
}, {
  "name" : "com.azure.resourcemanager.sqlvirtualmachine.models.Commit",
  "allDeclaredConstructors" : true,
  "allDeclaredFields" : true,
  "allDeclaredMethods" : true
}, {
  "name" : "com.azure.resourcemanager.sqlvirtualmachine.models.Failover",
  "allDeclaredConstructors" : true,
  "allDeclaredFields" : true,
  "allDeclaredMethods" : true
}, {
  "name" : "com.azure.resourcemanager.sqlvirtualmachine.models.ReadableSecondary",
  "allDeclaredConstructors" : true,
  "allDeclaredFields" : true,
  "allDeclaredMethods" : true
}, {
  "name" : "com.azure.resourcemanager.sqlvirtualmachine.models.OperationOrigin",
  "allDeclaredConstructors" : true,
  "allDeclaredFields" : true,
  "allDeclaredMethods" : true
}, {
  "name" : "com.azure.resourcemanager.sqlvirtualmachine.models.SqlVmGroupImageSku",
  "allDeclaredConstructors" : true,
  "allDeclaredFields" : true,
  "allDeclaredMethods" : true
}, {
  "name" : "com.azure.resourcemanager.sqlvirtualmachine.models.ScaleType",
  "allDeclaredConstructors" : true,
  "allDeclaredFields" : true,
  "allDeclaredMethods" : true
}, {
  "name" : "com.azure.resourcemanager.sqlvirtualmachine.models.ClusterManagerType",
  "allDeclaredConstructors" : true,
  "allDeclaredFields" : true,
  "allDeclaredMethods" : true
}, {
  "name" : "com.azure.resourcemanager.sqlvirtualmachine.models.ClusterConfiguration",
  "allDeclaredConstructors" : true,
  "allDeclaredFields" : true,
  "allDeclaredMethods" : true
}, {
  "name" : "com.azure.resourcemanager.sqlvirtualmachine.models.ClusterSubnetType",
  "allDeclaredConstructors" : true,
  "allDeclaredFields" : true,
  "allDeclaredMethods" : true
}, {
  "name" : "com.azure.resourcemanager.sqlvirtualmachine.models.IdentityType",
  "allDeclaredConstructors" : true,
  "allDeclaredFields" : true,
  "allDeclaredMethods" : true
}, {
  "name" : "com.azure.resourcemanager.sqlvirtualmachine.models.SqlServerLicenseType",
  "allDeclaredConstructors" : true,
  "allDeclaredFields" : true,
  "allDeclaredMethods" : true
}, {
  "name" : "com.azure.resourcemanager.sqlvirtualmachine.models.SqlManagementMode",
  "allDeclaredConstructors" : true,
  "allDeclaredFields" : true,
  "allDeclaredMethods" : true
}, {
  "name" : "com.azure.resourcemanager.sqlvirtualmachine.models.LeastPrivilegeMode",
  "allDeclaredConstructors" : true,
  "allDeclaredFields" : true,
  "allDeclaredMethods" : true
}, {
  "name" : "com.azure.resourcemanager.sqlvirtualmachine.models.SqlImageSku",
  "allDeclaredConstructors" : true,
  "allDeclaredFields" : true,
  "allDeclaredMethods" : true
}, {
  "name" : "com.azure.resourcemanager.sqlvirtualmachine.models.AdditionalVmPatch",
  "allDeclaredConstructors" : true,
  "allDeclaredFields" : true,
  "allDeclaredMethods" : true
}, {
  "name" : "com.azure.resourcemanager.sqlvirtualmachine.models.BackupScheduleType",
  "allDeclaredConstructors" : true,
  "allDeclaredFields" : true,
  "allDeclaredMethods" : true
}, {
  "name" : "com.azure.resourcemanager.sqlvirtualmachine.models.FullBackupFrequencyType",
  "allDeclaredConstructors" : true,
  "allDeclaredFields" : true,
  "allDeclaredMethods" : true
}, {
  "name" : "com.azure.resourcemanager.sqlvirtualmachine.models.AutoBackupDaysOfWeek",
  "allDeclaredConstructors" : true,
  "allDeclaredFields" : true,
  "allDeclaredMethods" : true
}, {
  "name" : "com.azure.resourcemanager.sqlvirtualmachine.models.ConnectivityType",
  "allDeclaredConstructors" : true,
  "allDeclaredFields" : true,
  "allDeclaredMethods" : true
}, {
  "name" : "com.azure.resourcemanager.sqlvirtualmachine.models.SqlWorkloadType",
  "allDeclaredConstructors" : true,
  "allDeclaredFields" : true,
  "allDeclaredMethods" : true
}, {
  "name" : "com.azure.resourcemanager.sqlvirtualmachine.models.DiskConfigurationType",
  "allDeclaredConstructors" : true,
  "allDeclaredFields" : true,
  "allDeclaredMethods" : true
}, {
  "name" : "com.azure.resourcemanager.sqlvirtualmachine.models.StorageWorkloadType",
  "allDeclaredConstructors" : true,
  "allDeclaredFields" : true,
  "allDeclaredMethods" : true
}, {
  "name" : "com.azure.resourcemanager.sqlvirtualmachine.models.TroubleshootingScenario",
  "allDeclaredConstructors" : true,
  "allDeclaredFields" : true,
  "allDeclaredMethods" : true
}, {
  "name" : "com.azure.resourcemanager.sqlvirtualmachine.models.DayOfWeek",
  "allDeclaredConstructors" : true,
  "allDeclaredFields" : true,
  "allDeclaredMethods" : true
}, {
  "name" : "com.azure.resourcemanager.sqlvirtualmachine.models.AssessmentDayOfWeek",
  "allDeclaredConstructors" : true,
  "allDeclaredFields" : true,
  "allDeclaredMethods" : true
} ]