{
  "flavor": "Azure", 
  "CrossLanguageDefinitionId": {
    "com.azure.healthdataaiservices.deid.DeidentificationClientBuilder": "HealthDataAIServices.Deidentification.DeidentificationClient",
    "com.azure.healthdataaiservices.deid.JobsAsyncClient": "null",
    "com.azure.healthdataaiservices.deid.JobsAsyncClient.beginCreate": "HealthDataAIServices.Deidentification.Jobs.create",
    "com.azure.healthdataaiservices.deid.JobsAsyncClient.beginCreateWithModel": "HealthDataAIServices.Deidentification.Jobs.create",
    "com.azure.healthdataaiservices.deid.JobsAsyncClient.cancel": "HealthDataAIServices.Deidentification.Jobs.cancel",
    "com.azure.healthdataaiservices.deid.JobsAsyncClient.cancelWithResponse": "HealthDataAIServices.Deidentification.Jobs.cancel",
    "com.azure.healthdataaiservices.deid.JobsAsyncClient.delete": "HealthDataAIServices.Deidentification.Jobs.delete",
    "com.azure.healthdataaiservices.deid.JobsAsyncClient.deleteWithResponse": "HealthDataAIServices.Deidentification.Jobs.delete",
    "com.azure.healthdataaiservices.deid.JobsAsyncClient.get": "HealthDataAIServices.Deidentification.Jobs.get",
    "com.azure.healthdataaiservices.deid.JobsAsyncClient.getWithResponse": "HealthDataAIServices.Deidentification.Jobs.get",
    "com.azure.healthdataaiservices.deid.JobsAsyncClient.list": "HealthDataAIServices.Deidentification.Jobs.list",
    "com.azure.healthdataaiservices.deid.JobsAsyncClient.listFiles": "HealthDataAIServices.Deidentification.Jobs.listFiles",
    "com.azure.healthdataaiservices.deid.JobsClient": "null",
    "com.azure.healthdataaiservices.deid.JobsClient.beginCreate": "HealthDataAIServices.Deidentification.Jobs.create",
    "com.azure.healthdataaiservices.deid.JobsClient.beginCreateWithModel": "HealthDataAIServices.Deidentification.Jobs.create",
    "com.azure.healthdataaiservices.deid.JobsClient.cancel": "HealthDataAIServices.Deidentification.Jobs.cancel",
    "com.azure.healthdataaiservices.deid.JobsClient.cancelWithResponse": "HealthDataAIServices.Deidentification.Jobs.cancel",
    "com.azure.healthdataaiservices.deid.JobsClient.delete": "HealthDataAIServices.Deidentification.Jobs.delete",
    "com.azure.healthdataaiservices.deid.JobsClient.deleteWithResponse": "HealthDataAIServices.Deidentification.Jobs.delete",
    "com.azure.healthdataaiservices.deid.JobsClient.get": "HealthDataAIServices.Deidentification.Jobs.get",
    "com.azure.healthdataaiservices.deid.JobsClient.getWithResponse": "HealthDataAIServices.Deidentification.Jobs.get",
    "com.azure.healthdataaiservices.deid.JobsClient.list": "HealthDataAIServices.Deidentification.Jobs.list",
    "com.azure.healthdataaiservices.deid.JobsClient.listFiles": "HealthDataAIServices.Deidentification.Jobs.listFiles",
    "com.azure.healthdataaiservices.deid.RealtimeOperationsAsyncClient": "null",
    "com.azure.healthdataaiservices.deid.RealtimeOperationsAsyncClient.deid": "HealthDataAIServices.Deidentification.RealtimeOperations.deid",
    "com.azure.healthdataaiservices.deid.RealtimeOperationsAsyncClient.deidWithResponse": "HealthDataAIServices.Deidentification.RealtimeOperations.deid",
    "com.azure.healthdataaiservices.deid.RealtimeOperationsClient": "null",
    "com.azure.healthdataaiservices.deid.RealtimeOperationsClient.deid": "HealthDataAIServices.Deidentification.RealtimeOperations.deid",
    "com.azure.healthdataaiservices.deid.RealtimeOperationsClient.deidWithResponse": "HealthDataAIServices.Deidentification.RealtimeOperations.deid",
    "com.azure.healthdataaiservices.deid.models.DeidRequest": "HealthDataAIServices.Deidentification.DeidRequest",
    "com.azure.healthdataaiservices.deid.models.DeidResponse": "HealthDataAIServices.Deidentification.DeidResponse",
    "com.azure.healthdataaiservices.deid.models.DocumentDataType": "HealthDataAIServices.Deidentification.DocumentDataType",
    "com.azure.healthdataaiservices.deid.models.File": "HealthDataAIServices.Deidentification.File",
    "com.azure.healthdataaiservices.deid.models.FileLocation": "HealthDataAIServices.Deidentification.FileLocation",
    "com.azure.healthdataaiservices.deid.models.Job": "HealthDataAIServices.Deidentification.Job",
    "com.azure.healthdataaiservices.deid.models.JobStatus": "HealthDataAIServices.Deidentification.JobStatus",
    "com.azure.healthdataaiservices.deid.models.JobSummary": "HealthDataAIServices.Deidentification.JobSummary",
    "com.azure.healthdataaiservices.deid.models.OperationState": "Azure.Core.Foundations.OperationState",
    "com.azure.healthdataaiservices.deid.models.OperationType": "HealthDataAIServices.Deidentification.OperationType",
    "com.azure.healthdataaiservices.deid.models.PhiCategory": "HealthDataAIServices.Deidentification.PhiCategory",
    "com.azure.healthdataaiservices.deid.models.PhiEntity": "HealthDataAIServices.Deidentification.PhiEntity",
    "com.azure.healthdataaiservices.deid.models.PhiTaggerResult": "HealthDataAIServices.Deidentification.PhiTaggerResult",
    "com.azure.healthdataaiservices.deid.models.SourceStorageLocation": "HealthDataAIServices.Deidentification.SourceStorageLocation",
    "com.azure.healthdataaiservices.deid.models.StringIndexType": "HealthDataAIServices.Deidentification.StringIndexType",
    "com.azure.healthdataaiservices.deid.models.TargetStorageLocation": "HealthDataAIServices.Deidentification.TargetStorageLocation"
  }
}
